{
  "_class": "shapeGroup",
  "clippingMaskMode": 0,
  "do_objectID": "07000B5D-5C28-431F-B111-6C4F8EA6A47D",
  "exportOptions": {
    "_class": "exportOptions",
    "exportFormats": [
    ],
    "includedLayerIds": [
    ],
    "layerOptions": 0,
    "shouldTrim": false
  },
  "frame": {
    "_class": "rect",
    "constrainProportions": true,
    "height": 24,
    "width": 24,
    "x": 2,
    "y": 2
  },
  "hasClickThrough": true,
  "hasClippingMask": true,
  "isFlippedHorizontal": false,
  "isFlippedVertical": false,
  "isLocked": false,
  "isVisible": false,
  "layerListExpandedType": 0,
  "layers": [
    {
      "class": "shapePath",
      "id": "6B577D97-0CB7-4B87-85E2-5F0E6F451A70"
    },
    {
      "class": "shapePath",
      "id": "48AC6898-93D3-4F6C-98A7-C607121E6FD5"
    }
  ],
  "name": "Oval",
  "nameIsFixed": false,
  "resizingConstraint": 63,
  "resizingType": 0,
  "rotation": 0,
  "shouldBreakMaskChain": false,
  "style": {
    "_class": "style",
    "blur": {
      "_class": "blur",
      "center": "{0.5, 0.5}",
      "isEnabled": false,
      "motionAngle": 0,
      "radius": 5,
      "type": 0
    },
    "endDecorationType": 0,
    "fills": [
      {
        "_class": "fill",
        "color": {
          "_class": "color",
          "alpha": 1,
          "blue": 0.4784313725490196,
          "green": 0.4549019607843137,
          "red": 0.4235294117647059
        },
        "fillType": 0,
        "isEnabled": false,
        "noiseIndex": 0,
        "noiseIntensity": 0,
        "patternFillType": 1,
        "patternTileScale": 1
      }
    ],
    "miterLimit": 10,
    "startDecorationType": 0
  },
  "userInfo": {
    "com.animaapp.stc-sketch-plugin": {
      "kModelPropertiesKey": {
        "constraints": {
          "aspectRatio": {
            "constant": 24,
            "enabled": 1,
            "modelID": "constraint_ed8d7c55-f8ef-43fe-b5ad-d4982a0b700f",
            "model_class": "ADModelConstraint",
            "model_version": 0.1,
            "multiplier": 24
          },
          "automatic": 1,
          "modelID": "viewConstraints_df3ed0b2-6459-43c8-9cb2-26ebb5a4a757",
          "model_class": "ADModelViewConstraints",
          "model_version": 0.1,
          "scaleFactor": 1
        }
      }
    }
  },
  "windingRule": 0
}